odoo/addons/iot_output_oca/README.rst
odoo/addons/iot_output_oca/__init__.py
odoo/addons/iot_output_oca/__manifest__.py
odoo/addons/iot_output_oca/i18n/iot_output.pot
odoo/addons/iot_output_oca/i18n/iot_output_oca.pot
odoo/addons/iot_output_oca/migrations/14.0.1.0.0/pre-migration.py
odoo/addons/iot_output_oca/models/__init__.py
odoo/addons/iot_output_oca/models/iot_communication_system.py
odoo/addons/iot_output_oca/models/iot_device.py
odoo/addons/iot_output_oca/models/iot_device_output.py
odoo/addons/iot_output_oca/models/iot_device_output_action.py
odoo/addons/iot_output_oca/readme/CONTRIBUTORS.rst
odoo/addons/iot_output_oca/readme/DESCRIPTION.rst
odoo/addons/iot_output_oca/security/ir.model.access.csv
odoo/addons/iot_output_oca/static/description/icon.png
odoo/addons/iot_output_oca/static/description/index.html
odoo/addons/iot_output_oca/tests/__init__.py
odoo/addons/iot_output_oca/tests/test_iot.py
odoo/addons/iot_output_oca/views/iot_device_output_views.xml
odoo/addons/iot_output_oca/views/iot_device_views.xml
odoo14_addon_iot_output_oca-14.0.1.0.2.dist-info/METADATA
odoo14_addon_iot_output_oca-14.0.1.0.2.dist-info/WHEEL
odoo14_addon_iot_output_oca-14.0.1.0.2.dist-info/top_level.txt
odoo14_addon_iot_output_oca-14.0.1.0.2.dist-info/RECORD
